is_even/__init__.py
is_even-1.0.7.dist-info/METADATA
is_even-1.0.7.dist-info/WHEEL
is_even-1.0.7.dist-info/licenses/LICENSE
is_even-1.0.7.dist-info/RECORD
