Metadata-Version: 2.1
Name: is-even
Version: 1.0.7
Summary: Return true if the given number is even.
Project-URL: Homepage, https://github.com/victorbnl/is-even
Project-URL: Tracker, https://github.com/victorbnl/is-even/issues
Project-URL: Source, https://github.com/victorbnl/is-even
Author-email: Victor Bonnelle <victor.bonnelle@proton.me>
License-Expression: MIT
License-File: LICENSE
